{
  "name": "Yordan Ivanov",
  "tagline": "Head of Data Engineering",
  "description": "I help Data Engineers handle the side of the job that isn't code. I write about how to actually own a project, navigate the market, and get promoted without becoming a corporate politician.",
  "siteUrl": "https://www.ivanovyordan.com",
  "email": "hi@ivanovyordan.com",
  "bookingUrl": "https://tidycal.com/ivanovyordan/discovery-call",
  "analytics": {
    "googleAnalyticsId": "G-ZBQYHRPLK1",
    "facebookPixelId": "1177345760364341"
  },
  "newsletter": {
    "service": "listmonk",
    "url": "https://newsletter.ivanovyordan.com/subscription/form",
    "listmonk": {
      "baseUrl": "https://newsletter.ivanovyordan.com",
      "lists": [
        {
          "id": "fd3b8a08-a51f-40fc-b255-3ce353d07c41",
          "label": "Everybody",
          "checked": true
        }
      ]
    }
  },
  "errorTracking": {
    "sentryDsn": "https://474338cee218a42288f937ad2ac363a5@o133364.ingest.us.sentry.io/4510716479864832",
    "environment": "production"
  },
  "social": [
    {
      "label": "LinkedIn",
      "url": "https://www.linkedin.com/in/ivanovyordan/",
      "platform": "linkedin"
    },
    {
      "label": "Substack",
      "url": "https://substack.com/@ivanovyordan",
      "platform": "substack"
    },
    {
      "label": "Twitter",
      "url": "https://x.com/heyivanovyordan",
      "platform": "twitter"
    }
  ],
  "seo": {
    "defaultTitle": "Yordan Ivanov - Head of Data Engineering",
    "defaultDescription": "Data engineering leadership, architecture, and coaching."
  },
  "blog": {
    "title": "Blog",
    "description": "Thinking out loud about data engineering, leadership, and systems.",
    "initialPosts": 12,
    "postsPerLoad": 6
  }
}